mycalc/calculator.py
hanjaekim-1.1.1.dist-info/METADATA
hanjaekim-1.1.1.dist-info/WHEEL
hanjaekim-1.1.1.dist-info/top_level.txt
hanjaekim-1.1.1.dist-info/RECORD
