Metadata-Version: 2.1
Name: hanjaekim
Version: 1.1.1
Summary: oss-nice calc
Home-page: https://github.com/Kimhanjae7/oss-setuptools
Download-URL: https://github.com/Kimhanjae7/oss-setuptools/v1.1.1.zip
Author: hanjaekim
Author-email: hjk2512@naver.com
License: UNKNOWN
Platform: UNKNOWN
Classifier: Programming Language :: Python :: 3
